merpe/__init__.py
merpe/core.py
merpe-3.3.1.dist-info/METADATA
merpe-3.3.1.dist-info/WHEEL
merpe-3.3.1.dist-info/top_level.txt
merpe-3.3.1.dist-info/RECORD
